stream_llm_parser/__init__.py
stream_llm_parser/base_parser.py
stream_llm_parser-0.1.1.dist-info/licenses/LICENSE
stream_llm_parser-0.1.1.dist-info/METADATA
stream_llm_parser-0.1.1.dist-info/WHEEL
stream_llm_parser-0.1.1.dist-info/top_level.txt
stream_llm_parser-0.1.1.dist-info/RECORD
