Metadata-Version: 2.4
Name: stream_llm_parser
Version: 0.1.1
Summary: stream_llm_parser is a Python library for parsing and processing streaming data with special token handling.
Home-page: https://github.com/TING2938/stream_llm_parser
Author: Ye Ting
Author-email: yeting2938@163.com
License: MIT
License-File: LICENSE
Dynamic: author
Dynamic: author-email
Dynamic: description
Dynamic: description-content-type
Dynamic: home-page
Dynamic: license
Dynamic: license-file
Dynamic: summary
